paderborn_bearing/__init__.py
paderborn_bearing/datafiles.txt
paderborn_bearing-1.1.2.dist-info/METADATA
paderborn_bearing-1.1.2.dist-info/WHEEL
paderborn_bearing-1.1.2.dist-info/top_level.txt
paderborn_bearing-1.1.2.dist-info/RECORD
