Metadata-Version: 2.4
Name: paderborn_bearing
Version: 1.1.2
Summary: Preprocessed Paderborn Bearing Dataset for analysing multivariate motor current signals combined with a vibration signal
Home-page: https://github.com/JvdHoogen/paderborn_bearing
Author: Jurgen van den Hoogen
Author-email: jurgenvandenhoogen@hotmail.com
Classifier: Programming Language :: Python :: 3
Classifier: License :: OSI Approved :: MIT License
Classifier: Operating System :: OS Independent
Requires-Python: >=3.9
Dynamic: author
Dynamic: author-email
Dynamic: classifier
Dynamic: description
Dynamic: description-content-type
Dynamic: home-page
Dynamic: requires-python
Dynamic: summary
